<annotation>
	<folder>Images</folder>
	<filename>16.jpg</filename>
	<path>E:\Army Courses\MIST\Level-4\Term-2\IDP_\Machine Learning\Images\16.jpg</path>
	<source>
		<database>Unknown</database>
	</source>
	<size>
		<width>280</width>
		<height>505</height>
		<depth>3</depth>
	</size>
	<segmented>0</segmented>
	<object>
		<name>Bullet</name>
		<pose>Unspecified</pose>
		<truncated>0</truncated>
		<difficult>0</difficult>
		<bndbox>
			<xmin>113</xmin>
			<ymin>234</ymin>
			<xmax>121</xmax>
			<ymax>244</ymax>
		</bndbox>
	</object>
	<object>
		<name>Bullet</name>
		<pose>Unspecified</pose>
		<truncated>0</truncated>
		<difficult>0</difficult>
		<bndbox>
			<xmin>161</xmin>
			<ymin>228</ymin>
			<xmax>169</xmax>
			<ymax>238</ymax>
		</bndbox>
	</object>
	<object>
		<name>Bullet</name>
		<pose>Unspecified</pose>
		<truncated>0</truncated>
		<difficult>0</difficult>
		<bndbox>
			<xmin>134</xmin>
			<ymin>293</ymin>
			<xmax>141</xmax>
			<ymax>302</ymax>
		</bndbox>
	</object>
	<object>
		<name>Bullet</name>
		<pose>Unspecified</pose>
		<truncated>0</truncated>
		<difficult>0</difficult>
		<bndbox>
			<xmin>192</xmin>
			<ymin>311</ymin>
			<xmax>200</xmax>
			<ymax>321</ymax>
		</bndbox>
	</object>
</annotation>
